packaging2/__init__.py
packaging2/my_file.py
packaging2/my_other_file.py
packaging2/states_info.py
packaging2/my_folder/__init__.py
packaging2/my_folder/my_nested_file.py
packaging2/my_folder/sub_package/__init__.py
fun_packaging-0.0.0.dist-info/METADATA
fun_packaging-0.0.0.dist-info/WHEEL
fun_packaging-0.0.0.dist-info/top_level.txt
fun_packaging-0.0.0.dist-info/RECORD
