Metadata-Version: 2.1
Name: fun-packaging
Version: 0.0.0
Summary: My package built during the Udemy Python to Production course
Author: Josiah Carberry
Author-email: Morgan Sell <morganpsell@gmail.com>
Keywords: python
Requires-Python: >=3.9
Requires-Dist: requests
Requires-Dist: importlib-metadata; python_version < "3.11"
Provides-Extra: dev
Requires-Dist: packaging2[release,static-code-qa,test]; extra == "dev"
Provides-Extra: pdf
Requires-Dist: ReportLab>=1.2; extra == "pdf"
Requires-Dist: RXP; extra == "pdf"
Provides-Extra: release
Requires-Dist: build; extra == "release"
Requires-Dist: twine; extra == "release"
Provides-Extra: rest
Requires-Dist: docutils>=0.3; extra == "rest"
Requires-Dist: pack==1.1,==1.3; extra == "rest"
Provides-Extra: static-code-qa
Requires-Dist: pre-commit; extra == "static-code-qa"
Provides-Extra: test
Requires-Dist: pytest; extra == "test"
Requires-Dist: pytest-cov; extra == "test"
